veides/__init__.py
veides/sdk/__init__.py
veides/sdk/agent/__init__.py
veides/sdk/agent/base_client.py
veides/sdk/agent/client.py
veides/sdk/agent/exceptions.py
veides/sdk/agent/properties.py
veides_agent_sdk-0.4.0.dist-info/LICENSE
veides_agent_sdk-0.4.0.dist-info/METADATA
veides_agent_sdk-0.4.0.dist-info/WHEEL
veides_agent_sdk-0.4.0.dist-info/top_level.txt
veides_agent_sdk-0.4.0.dist-info/RECORD
